cmeel.pth
cmeel_pth.py
cmeel/__init__.py
cmeel/__main__.py
cmeel/backports.py
cmeel/build.py
cmeel/cmeel.py
cmeel/config.py
cmeel/consts.py
cmeel/docker.py
cmeel/env.py
cmeel/impl.py
cmeel/metadata.py
cmeel/release.py
cmeel/run.py
cmeel/sdist.py
cmeel/utils.py
cmeel-0.58.0.dist-info/METADATA
cmeel-0.58.0.dist-info/WHEEL
cmeel-0.58.0.dist-info/entry_points.txt
cmeel-0.58.0.dist-info/licenses/LICENSE
cmeel-0.58.0.dist-info/RECORD
