Metadata-Version: 2.4
Name: cmeel
Version: 0.58.0
Summary: Create Wheel from CMake projects
Project-URL: Changelog, https://github.com/cmake-wheel/cmeel/blob/main/CHANGELOG.md
Project-URL: Documentation, https://cmeel.readthedocs.io/
Project-URL: Homepage, https://github.com/cmake-wheel/cmeel
Author-email: Guilhem Saurel <guilhem.saurel@laas.fr>
License-Expression: BSD-2-Clause
License-File: LICENSE
Classifier: Operating System :: MacOS
Classifier: Operating System :: POSIX :: Linux
Classifier: Programming Language :: C++
Classifier: Programming Language :: Python :: 3
Classifier: Topic :: Software Development :: Build Tools
Classifier: Topic :: System :: Archiving :: Packaging
Classifier: Topic :: System :: Software Distribution
Requires-Python: >=3.9
Requires-Dist: tomli>=2.1.0; python_full_version < '3.11'
Provides-Extra: build
Requires-Dist: cmake>=3.31.2; extra == 'build'
Requires-Dist: git-archive-all; extra == 'build'
Requires-Dist: packaging>=24.2; extra == 'build'
Requires-Dist: wheel>=0.45.1; extra == 'build'
